compressed_image/py.typed
compressed_image/__init__.py
compressed_image/include/pybind11_json/pybind11_json.hpp
compressed_image/lib/compressed_image.cp311-win_amd64.pyd
compressed_image/share/cmake/pybind11_json/pybind11_jsonConfig.cmake
compressed_image/share/cmake/pybind11_json/pybind11_jsonConfigVersion.cmake
compressed_image/share/cmake/pybind11_json/pybind11_jsonTargets.cmake
compressed_image/share/pkgconfig/pybind11_json.pc
compressed_image/_stubs/_compressed_image.pyi
compressed_image/_stubs/__init__.pyi
compressed_image-1.0.1.dist-info/DELVEWHEEL
compressed_image-1.0.1.dist-info/METADATA
compressed_image-1.0.1.dist-info/RECORD
compressed_image-1.0.1.dist-info/WHEEL
compressed_image-1.0.1.dist-info/licenses/LICENSE
compressed_image.libs/boost_filesystem-vc143-mt-x64-1_88-7faae932b8f37d016f480b322e468195.dll
compressed_image.libs/boost_thread-vc143-mt-x64-1_88-110a16c79b61db8b6eba0716d0f9933d.dll
compressed_image.libs/deflate-b37e83b6af15d56d6860cf186b3e2bc6.dll
compressed_image.libs/Iex-3_3-6ce9089fd08ebb6fca61621c6dff1791.dll
compressed_image.libs/IlmThread-3_3-617f1b7bc83f0525251c450f2560b5b1.dll
compressed_image.libs/Imath-3_1-b4cf586e9bcfc7f4e5e34186d19f82cb.dll
compressed_image.libs/jpeg62-fd333376cf4b34b878702816184c41a0.dll
compressed_image.libs/liblzma-f3814251d837098a88b0107c35068362.dll
compressed_image.libs/libpng16-9dac047321cd0eab5751791941293d71.dll
compressed_image.libs/msvcp140-a4c2229bdc2a2a630acdc095b4d86008.dll
compressed_image.libs/msvcp140_atomic_wait-eb238a7437cff8f49c01cc67fd035163.dll
compressed_image.libs/msvcp140_codecvt_ids-f2069a52880ec885ee7f0511186100eb.dll
compressed_image.libs/OpenEXR-3_3-7d2c03cb06bc1da7e3b4399ce04dc2e7.dll
compressed_image.libs/OpenEXRCore-3_3-be699cf6b5ba5982fb49a2626a6699aa.dll
compressed_image.libs/OpenImageIO-de11ac489ba78a4d28b1deeaae7febb8.dll
compressed_image.libs/OpenImageIO_Util-080a114f958fdf76111903be65327d1f.dll
compressed_image.libs/tiff-d53500c9e65e392b3cfbcd80ba810d0a.dll
compressed_image.libs/zlib1-5b3400ac5a3aa3da757366b123da1894.dll
