Metadata-Version: 2.2
Name: compressed-image
Version: 1.0.1
Summary: Fast and memory-efficient, compressed in-memory image storage for C++ and Python.
Author-Email: Emil Dohne <emildohne@gmail.com>
Maintainer-Email: Emil Dohne <emildohne@gmail.com>
License: BSD-3-Clause
Project-URL: Homepage, https://compressed-image.readthedocs.io/en/latest/
Project-URL: Source, https://github.com/EmilDohne/compressed-image
Project-URL: Documentation, https://compressed-image.readthedocs.io/en/latest/
Project-URL: Issues, https://github.com/EmilDohne/compressed-image/issues
Requires-Python: >=3.9
Requires-Dist: numpy
